mabandit/__init__.py
mabandit/Data_structures/Priority_queue.py
mabandit/Data_structures/__init__.py
mabandit/Kernals/RBF.py
mabandit/Kernals/__init__.py
mabandit/Machine_learning/Bayesian_neural_network.py
mabandit/Machine_learning/Beta_bernoulli_model.py
mabandit/Machine_learning/Gaussian_process.py
mabandit/Machine_learning/__init__.py
mabandit/Multi_arm_bandit_algorithms/__init__.py
mabandit/Multi_arm_bandit_algorithms/Adaptive_algorithms/__init__.py
mabandit/Multi_arm_bandit_algorithms/Baysian_bandits/Thomspson_sampling.py
mabandit/Multi_arm_bandit_algorithms/Baysian_bandits/__init__.py
mabandit/Multi_arm_bandit_algorithms/GP_bandits/Expected_improvement.py
mabandit/Multi_arm_bandit_algorithms/GP_bandits/Explore_exploit_tradeoff.py
mabandit/Multi_arm_bandit_algorithms/GP_bandits/Probability_of_improvement.py
mabandit/Multi_arm_bandit_algorithms/GP_bandits/__init__.py
mabandit/Multi_arm_bandit_algorithms/Non_adaptive_algoritms/Epislon_greedy.py
mabandit/Multi_arm_bandit_algorithms/Non_adaptive_algoritms/Explore_first.py
mabandit/Multi_arm_bandit_algorithms/Non_adaptive_algoritms/__init__.py
mabandit-1.3.dist-info/DESCRIPTION.rst
mabandit-1.3.dist-info/METADATA
mabandit-1.3.dist-info/RECORD
mabandit-1.3.dist-info/WHEEL
mabandit-1.3.dist-info/metadata.json
mabandit-1.3.dist-info/top_level.txt
